mypassmaker/__init__.py
mypassmaker-1.4.dist-info/LICENSE
mypassmaker-1.4.dist-info/METADATA
mypassmaker-1.4.dist-info/WHEEL
mypassmaker-1.4.dist-info/top_level.txt
mypassmaker-1.4.dist-info/RECORD
