Metadata-Version: 2.2
Name: mypassmaker
Version: 1.4
Summary: Generate and safty check secure password
Home-page: https://github.com/edrisranjbar/secure_password_generator
Author: Edris Ranjbar
Author-email: edris.qeshm2@gmail.com
License: MIT
Classifier: Programming Language :: Python :: 3
Classifier: License :: OSI Approved :: MIT License
Classifier: Operating System :: OS Independent
Requires-Python: >=3.6
License-File: LICENSE
Dynamic: author
Dynamic: author-email
Dynamic: classifier
Dynamic: description
Dynamic: description-content-type
Dynamic: home-page
Dynamic: license
Dynamic: requires-python
Dynamic: summary
